pyCombinatorial/__init__.py
pyCombinatorial/algorithm/__init__.py
pyCombinatorial/algorithm/aco.py
pyCombinatorial/algorithm/alns.py
pyCombinatorial/algorithm/bb.py
pyCombinatorial/algorithm/bf.py
pyCombinatorial/algorithm/bhk.py
pyCombinatorial/algorithm/brkga.py
pyCombinatorial/algorithm/bt.py
pyCombinatorial/algorithm/christofides.py
pyCombinatorial/algorithm/conc_hull.py
pyCombinatorial/algorithm/conv_hull.py
pyCombinatorial/algorithm/cw.py
pyCombinatorial/algorithm/eln.py
pyCombinatorial/algorithm/eo.py
pyCombinatorial/algorithm/frnn.py
pyCombinatorial/algorithm/ga.py
pyCombinatorial/algorithm/gksp.py
pyCombinatorial/algorithm/grasp.py
pyCombinatorial/algorithm/hpn.py
pyCombinatorial/algorithm/ins_c.py
pyCombinatorial/algorithm/ins_f.py
pyCombinatorial/algorithm/ins_n.py
pyCombinatorial/algorithm/ins_r.py
pyCombinatorial/algorithm/ksp.py
pyCombinatorial/algorithm/lns.py
pyCombinatorial/algorithm/mf.py
pyCombinatorial/algorithm/nn.py
pyCombinatorial/algorithm/opt_2.py
pyCombinatorial/algorithm/opt_2_5.py
pyCombinatorial/algorithm/opt_2_5s.py
pyCombinatorial/algorithm/opt_2s.py
pyCombinatorial/algorithm/opt_3.py
pyCombinatorial/algorithm/opt_3s.py
pyCombinatorial/algorithm/opt_4.py
pyCombinatorial/algorithm/opt_4s.py
pyCombinatorial/algorithm/opt_5.py
pyCombinatorial/algorithm/opt_5s.py
pyCombinatorial/algorithm/rl_double_ql.py
pyCombinatorial/algorithm/rl_ql.py
pyCombinatorial/algorithm/rl_sarsa.py
pyCombinatorial/algorithm/rr.py
pyCombinatorial/algorithm/rt.py
pyCombinatorial/algorithm/s_gui.py
pyCombinatorial/algorithm/s_itr.py
pyCombinatorial/algorithm/s_sct.py
pyCombinatorial/algorithm/s_shc.py
pyCombinatorial/algorithm/s_tabu.py
pyCombinatorial/algorithm/s_vns.py
pyCombinatorial/algorithm/sa.py
pyCombinatorial/algorithm/som.py
pyCombinatorial/algorithm/spfc_h.py
pyCombinatorial/algorithm/spfc_m.py
pyCombinatorial/algorithm/spfc_s.py
pyCombinatorial/algorithm/swp.py
pyCombinatorial/algorithm/tat.py
pyCombinatorial/algorithm/tbb.py
pycombinatorial-2.1.0.dist-info/LICENSE
pycombinatorial-2.1.0.dist-info/METADATA
pycombinatorial-2.1.0.dist-info/WHEEL
pycombinatorial-2.1.0.dist-info/top_level.txt
pycombinatorial-2.1.0.dist-info/RECORD
