Metadata-Version: 2.1
Name: pycombinatorial
Version: 2.1.0
Summary: A library to solve TSP (Travelling Salesman Problem) using Exact Algorithms, Heuristics, Metaheuristics and Reinforcement Learning
Home-page: https://github.com/Valdecy/pyCombinatorial
Author: Valdecy Pereira
Author-email: valdecy.pereira@gmail.com
License: GNU
License-File: LICENSE
Requires-Dist: folium
Requires-Dist: networkx
Requires-Dist: numpy
Requires-Dist: plotly
Requires-Dist: scipy
